qvalidate/Data_Truncation_specified_columns.py
qvalidate/__init__.py
qvalidate/check_duplicate.py
qvalidate/count_validation.py
qvalidate/data_date_validation.py
qvalidate/data_date_validation2.py
qvalidate/data_number_format_val.py
qvalidate/data_validation.py
qvalidate/data_validation_precesion.py
qvalidate/data_validation_precesion2.py
qvalidate/meta_data_length_validation.py
qvalidate/meta_data_validation.py
qvalidate/meta_data_validation_dtype.py
qvalidate/null_validation.py
qvalidate/out_of_range.py
qvalidate/rejected_record.py
qvalidate-0.0.2.dist-info/LICENSE
qvalidate-0.0.2.dist-info/METADATA
qvalidate-0.0.2.dist-info/WHEEL
qvalidate-0.0.2.dist-info/top_level.txt
qvalidate-0.0.2.dist-info/RECORD
